[

  {
    "image": "http://jackawilson.art/pages/art_board/pictures/Smiling_Amoeba.jpg",
    "header": "Smiling Amoeba",
    "description": "something fun from alcohol.",
    "link": null,
    "id": 1,
    "info": "6\" x 6\", alcohol ink, 2018",
    "copy": "Rainbow clouds surround the central subject, a similarly groovy little guy who's having a good time. Created by dropping alcohol ink on wax paper to create the colorful cloud like shapes featured."
  },

  {
    "image": "http://jackawilson.art/pages/art_board/pictures/YOINK.jpg",
    "header": "YOINK",
    "description": "A pigeon sneaks a bite.",
    "link": null
  },
  {
    "image": "http://jackawilson.art/pages/art_board/pictures/acthually.jpg",
    "header": "Acthually",
    "description": "We all know one.",
    "link": null
  },
  {
    "image": "http://jackawilson.art/pages/art_board/pictures/loisiu_lmaor.jpg",
    "header": "Loisie Lmaor",
    "description": "Best dime novelist of his time.",
    "link": null
  },
  {
    "image": "http://jackawilson.art/pages/art_board/pictures/chicagodog.png",
    "header": "Chicago Dog",
    "description": "No ketchup.",
    "link": null
  },
  {
    "image": "http://jackawilson.art/pages/art_board/pictures/sheep_clouds.png",
    "header": "Stopped Counting",
    "description": "These clouds are awfully sheepish.",
    "link": null
  },
  {
    "image": "http://jackawilson.art/pages/art_board/pictures/roads.png",
    "header": "roads",
    "description": "Take a walk.",
    "link": null
  },
  {
    "image": "http://jackawilson.art/pages/art_board/pictures/10_min.jpg",
    "header": "Ten Minutes",
    "description": "Taking a little outdoor break.",
    "link": null
  },
  {
    "image": "http://jackawilson.art/pages/art_board/pictures/right.jpg",
    "header": "Rightina",
    "description": "A lovely appendage.",
    "link": null
  },
  {
    "image": "http://jackawilson.art/pages/art_board/pictures/left.jpg",
    "header": "Lefton",
    "description": "Always lends a hand.",
    "link": null
  },
  {
    "image": "http://jackawilson.art/pages/art_board/pictures/lighthouse.png",
    "header": "Lighthouse",
    "description": "A guiding light in the night.",
    "link": null
  },
  {
    "image": "http://jackawilson.art/pages/art_board/pictures/cuircut.png",
    "header": "Circuit",
    "description": "Have you tried turning it on and off again?",
    "link": null
  }
]